README.md
setup.py
QuickDS/__init__.py
QuickDS/test.py
QuickDS.egg-info/PKG-INFO
QuickDS.egg-info/SOURCES.txt
QuickDS.egg-info/dependency_links.txt
QuickDS.egg-info/top_level.txt
QuickDS/implementations/__init__.py
QuickDS/implementations/binarysearchtree.py
QuickDS/implementations/inputformatter.py
QuickDS/implementations/linkedlist.py
QuickDS/implementations/list.py
QuickDS/implementations/node.py
QuickDS/implementations/treenode.py